setup.py
ureactme/__init__.py
ureactme/client.py
ureactme/models.py
ureactme.egg-info/PKG-INFO
ureactme.egg-info/SOURCES.txt
ureactme.egg-info/dependency_links.txt
ureactme.egg-info/requires.txt
ureactme.egg-info/top_level.txt