Metadata-Version: 1.1
Name: ureactme
Version: 0.2.4
Summary: UReact.me API lib
Home-page: https://github.com/pappacena/
Author: Thiago F. Pappacena
Author-email: pappacena@gmail.com
License: MIT
Platform: UNKNOWN
Classifier: Environment :: Web Environment
Classifier: Intended Audience :: Developers
Classifier: Operating System :: OS Independent
Classifier: Programming Language :: Python
Classifier: Programming Language :: Python :: 2.7
Classifier: Programming Language :: Python :: 3
Classifier: Programming Language :: Python :: 3.2
Classifier: Programming Language :: Python :: 3.3
Classifier: Programming Language :: Python :: 3.4
